{
  "general_refresh_rate": 100,
  "general_port": 34970,
  "general_skin_on_load": "default",
  "general_skin_locale": "en-EN",
  "general_job_remaining": "due_date",
  "general_h-shift-layout": "h-shifter",
  "unit_weight": "kg",
  "unit_length": "m",
  "unit_degrees": "C",
  "unit_consumption": "lpkm",
  "unit_volume": "l",
  "unit_pressure": "psi",
  "unit_speed": "kph",
  "unit_currency": "EUR",
  "InsanoDeath_elements_right_oilTemperature": "true",
  "InsanoDeath_elements_right_brakesTemperature": "true",
  "InsanoDeath_elements_right_brakesAirPressure": "true",
  "InsanoDeath_elements_right_fuel": "true",
  "InsanoDeath_elements_right_fuelConsumption": "true",
  "InsanoDeath_elements_right_cruiseControl": "true",
  "InsanoDeath_elements_right_waterTemperature": "true",
  "InsanoDeath_elements_right_batteryVoltage": true,
  "InsanoDeath_elements_mid_top_retarder": "true",
  "InsanoDeath_elements_mid_top_parkingBrake": "true",
  "InsanoDeath_elements_mid_top_beamHigh": "true",
  "InsanoDeath_elements_mid_top_beamLow": "true",
  "InsanoDeath_elements_mid_top_beacon": true,
  "InsanoDeath_elements_mid_bottom_rpm": "true",
  "InsanoDeath_elements_mid_bottom_fuel": "true",
  "InsanoDeath_elements_mid_bottom_speedLimit": "true",
  "InsanoDeath_elements_right_restStop": true,
  "InsanoDeath_elements_mid_bottom_blinker_turn": "true",
  "events_truck.refuel": true,
  "events_truck.damage": true,
  "events_truck.park": true,
  "events_truck.engine": true,
  "events_truck.electric": true,
  "events_truck.emergency": true,
  "events_truck.warning": true,
  "events_truck.cruise-control-decrease": true,
  "events_truck.cruise-control-increase": true,
  "events_truck.cruise-control": true,
  "events_trailers.damage": true,
  "events_trailers.coupling": true,
  "events_navigation.speed-limit": true,
  "events_job.started": true,
  "events_job.finished": true,
  "events_job.delivered": true,
  "events_job.cancelled": true,
  "events_game.refuel-payed": true,
  "events_game.train": true,
  "events_game.ferry": true,
  "events_game.tollgate": true,
  "events_game.fine": true,
  "events_game.pause": true,
  "maps_elements_eta": true,
  "maps_elements_speedAndGear": true,
  "maps_elements_mapControls": true,
  "maps_elements_speedLimit": true,
  "maps_elements_rotateWithPlayer": true,
  "maps_map_type": "vanilla",
  "maps_map_tilesRemotePath": "https://raw.githubusercontent.com/TwinDragon/SCS_Map_Tiles/master/",
  "maps_map_activeMap": null,
  "maps_map_navigationRemaining": "due_date",
  "maps_map_tilesVersion": "latest",
  "general_damage_accurate": "damage-diagnostic",
  "InsanoDeath_elements_right_map": true,
  "maps_map_tilesRemoteUseCustom": false,
  "maps_map_tilesRemoteCustomPath": null,
  "maps_general_debug": false
}